hue_logger/__init__.py
hue_logger/client.py
hue_logger-0.1.3.dist-info/licenses/LICENSE
hue_logger-0.1.3.dist-info/METADATA
hue_logger-0.1.3.dist-info/WHEEL
hue_logger-0.1.3.dist-info/top_level.txt
hue_logger-0.1.3.dist-info/RECORD
