Metadata-Version: 2.4
Name: hue_logger
Version: 0.1.3
Summary: A simple client for sending logs to the Hue Logs server.
Home-page: https://github.com/singh47/hue_logger_py_client
Author: Harman Singh
Author-email: harman@petdrifts.com
Classifier: Programming Language :: Python :: 3
Classifier: License :: OSI Approved :: MIT License
Classifier: Operating System :: OS Independent
Requires-Python: >=3.6
License-File: LICENSE
Requires-Dist: requests>=2.0.0
Dynamic: author
Dynamic: author-email
Dynamic: classifier
Dynamic: description
Dynamic: description-content-type
Dynamic: home-page
Dynamic: license-file
Dynamic: requires-dist
Dynamic: requires-python
Dynamic: summary
